github_status/__init__.py
github_status/github_status.py
github_status_cli-1.0.0.dist-info/METADATA
github_status_cli-1.0.0.dist-info/WHEEL
github_status_cli-1.0.0.dist-info/entry_points.txt
github_status_cli-1.0.0.dist-info/top_level.txt
github_status_cli-1.0.0.dist-info/RECORD
