Metadata-Version: 2.1
Name: github-status-cli
Version: 1.0.0
Summary: A small command-line tool that shows the current GitHub service status.
Author: Marcel Van Der Linde
License: MIT
Keywords: github,status,git,cli
Classifier: Programming Language :: Python :: 2
Classifier: Programming Language :: Python :: 3
Requires-Python: >=2.6
